LICENSE
MANIFEST.in
README
setup.cfg
setup.py
setup_helper.py
paraproxy/WrapSock.py
paraproxy/__init__.py
paraproxy.egg-info/PKG-INFO
paraproxy.egg-info/SOURCES.txt
paraproxy.egg-info/dependency_links.txt
paraproxy.egg-info/requires.txt
paraproxy.egg-info/top_level.txt