Metadata-Version: 1.0
Name: paraproxy
Version: 1.2
Summary: Paramiko addon for SSH2 ProxyCommands
Home-page: http://pypi.python.org/pypi/paraproxy/
Author: Rene Koecher
Author-email: shirk AT bitspin DOT org
License: LGPL
Platform: Posix; MacOS X
Classifier: Development Status :: 4 - Beta
Classifier: Intended Audience :: Developers
Classifier: License :: OSI Approved :: GNU Library or Lesser General Public License (LGPL)
Classifier: Operating System :: OS Independent
Classifier: Topic :: Internet
Classifier: Topic :: Security :: Cryptography
